{
  "info": {
    "_postman_id": "e6f7a8b9-c0d1-2345-efab-678901234567",
    "name": "Scanntech",
    "schema": "https://schema.getpostman.com/json/collection/v2.1.0/collection.json",
    "_exporter_id": "38872675",
    "description": "API de sincronização de estoque com a plataforma Scanntech. Autenticação Basic Auth (header `Authorization: Basic {{authToken}}`). Preencher `base_url_scanntech` e `companyId` no ambiente."
  },
  "item": [
    {
      "name": "Depósito",
      "item": [
        {
          "name": "GET Consultar Depósitos",
          "request": {
            "method": "GET",
            "header": [
              {
                "key": "Authorization",
                "value": "Basic {{authToken}}"
              }
            ],
            "url": {
              "raw": "{{base_url_scanntech}}/v2/companies/:companyId/store-warehouses",
              "host": [
                "{{base_url_scanntech}}"
              ],
              "path": [
                "v2",
                "companies",
                ":companyId",
                "store-warehouses"
              ],
              "variable": [
                {
                  "key": "companyId",
                  "value": "{{companyId}}"
                }
              ]
            }
          },
          "response": []
        },
        {
          "name": "POST Criar Depósito",
          "request": {
            "method": "POST",
            "header": [
              {
                "key": "Authorization",
                "value": "Basic {{authToken}}"
              },
              {
                "key": "Content-Type",
                "value": "application/json"
              }
            ],
            "body": {
              "mode": "raw",
              "raw": "{\n  \"id\": \"DEP-001\",\n  \"store_id\": \"1\",\n  \"description\": \"Deposito Principal\"\n}",
              "options": {
                "raw": {
                  "language": "json"
                }
              }
            },
            "url": {
              "raw": "{{base_url_scanntech}}/v2/companies/:companyId/store-warehouses",
              "host": [
                "{{base_url_scanntech}}"
              ],
              "path": [
                "v2",
                "companies",
                ":companyId",
                "store-warehouses"
              ],
              "variable": [
                {
                  "key": "companyId",
                  "value": "{{companyId}}"
                }
              ]
            }
          },
          "response": []
        },
        {
          "name": "PUT Atualizar Depósito",
          "request": {
            "method": "PUT",
            "header": [
              {
                "key": "Authorization",
                "value": "Basic {{authToken}}"
              },
              {
                "key": "Content-Type",
                "value": "application/json"
              }
            ],
            "body": {
              "mode": "raw",
              "raw": "{\n  \"id\": \"DEP-001\",\n  \"store_id\": \"1\",\n  \"description\": \"Deposito Principal Atualizado\"\n}",
              "options": {
                "raw": {
                  "language": "json"
                }
              }
            },
            "url": {
              "raw": "{{base_url_scanntech}}/v2/companies/:companyId/store-warehouses/:warehouseId",
              "host": [
                "{{base_url_scanntech}}"
              ],
              "path": [
                "v2",
                "companies",
                ":companyId",
                "store-warehouses",
                ":warehouseId"
              ],
              "variable": [
                {
                  "key": "companyId",
                  "value": "{{companyId}}"
                },
                {
                  "key": "warehouseId",
                  "value": ""
                }
              ]
            }
          },
          "response": []
        },
        {
          "name": "DELETE Excluir Depósito",
          "request": {
            "method": "DELETE",
            "header": [
              {
                "key": "Authorization",
                "value": "Basic {{authToken}}"
              }
            ],
            "url": {
              "raw": "{{base_url_scanntech}}/v2/companies/:companyId/store-warehouses/:warehouseId",
              "host": [
                "{{base_url_scanntech}}"
              ],
              "path": [
                "v2",
                "companies",
                ":companyId",
                "store-warehouses",
                ":warehouseId"
              ],
              "variable": [
                {
                  "key": "companyId",
                  "value": "{{companyId}}"
                },
                {
                  "key": "warehouseId",
                  "value": ""
                }
              ]
            }
          },
          "response": []
        }
      ]
    },
    {
      "name": "Embalagens",
      "item": [
        {
          "name": "POST Criar Embalagem",
          "request": {
            "method": "POST",
            "header": [
              {
                "key": "Authorization",
                "value": "Basic {{authToken}}"
              },
              {
                "key": "Content-Type",
                "value": "application/json"
              }
            ],
            "body": {
              "mode": "raw",
              "raw": "{\n  \"product_id\": \"7891234567890\",\n  \"product_barcode\": \"7891234567890\",\n  \"content_quantity\": 1.0\n}",
              "options": {
                "raw": {
                  "language": "json"
                }
              }
            },
            "url": {
              "raw": "{{base_url_scanntech}}/v2/companies/:companyId/warehouses/:warehouseId/packages",
              "host": [
                "{{base_url_scanntech}}"
              ],
              "path": [
                "v2",
                "companies",
                ":companyId",
                "warehouses",
                ":warehouseId",
                "packages"
              ],
              "variable": [
                {
                  "key": "companyId",
                  "value": "{{companyId}}"
                },
                {
                  "key": "warehouseId",
                  "value": ""
                }
              ]
            }
          },
          "response": []
        },
        {
          "name": "DELETE Excluir Embalagem",
          "request": {
            "method": "DELETE",
            "header": [
              {
                "key": "Authorization",
                "value": "Basic {{authToken}}"
              }
            ],
            "url": {
              "raw": "{{base_url_scanntech}}/v2/companies/:companyId/warehouses/:warehouseId/packages/:ean",
              "host": [
                "{{base_url_scanntech}}"
              ],
              "path": [
                "v2",
                "companies",
                ":companyId",
                "warehouses",
                ":warehouseId",
                "packages",
                ":ean"
              ],
              "variable": [
                {
                  "key": "companyId",
                  "value": "{{companyId}}"
                },
                {
                  "key": "warehouseId",
                  "value": ""
                },
                {
                  "key": "ean",
                  "value": ""
                }
              ]
            }
          },
          "response": []
        }
      ]
    },
    {
      "name": "Estoque",
      "item": [
        {
          "name": "POST Enviar Estoque",
          "request": {
            "method": "POST",
            "header": [
              {
                "key": "Authorization",
                "value": "Basic {{authToken}}"
              },
              {
                "key": "Content-Type",
                "value": "application/json"
              }
            ],
            "body": {
              "mode": "raw",
              "raw": "{\n  \"stock\": [\n    {\n      \"product_barcode\": \"7891234567890\",\n      \"stock_quantity\": 100.0\n    },\n    {\n      \"product_barcode\": \"7891234560001\",\n      \"stock_quantity\": 50.0\n    }\n  ]\n}",
              "options": {
                "raw": {
                  "language": "json"
                }
              }
            },
            "url": {
              "raw": "{{base_url_scanntech}}/v2/companies/:companyId/warehouses/:warehouseId/stock",
              "host": [
                "{{base_url_scanntech}}"
              ],
              "path": [
                "v2",
                "companies",
                ":companyId",
                "warehouses",
                ":warehouseId",
                "stock"
              ],
              "variable": [
                {
                  "key": "companyId",
                  "value": "{{companyId}}"
                },
                {
                  "key": "warehouseId",
                  "value": ""
                }
              ]
            }
          },
          "response": []
        }
      ]
    }
  ],
  "variable": [
    {
      "key": "base_url_scanntech",
      "value": "https://parceiro.scanntech.com/api-stock"
    },
    {
      "key": "companyId",
      "value": ""
    }
  ],
  "event": [
    {
      "listen": "test",
      "script": {
        "type": "text/javascript",
        "exec": [
          "pm.test('Status code 2xx', function() {",
          "    pm.response.to.be.success;",
          "});",
          "",
          "pm.test('Tempo de resposta < 3s', function() {",
          "    pm.expect(pm.response.responseTime).to.be.below(3000);",
          "});",
          "",
          "var ct = pm.response.headers.get('Content-Type');",
          "if (ct && ct.includes('application/json')) {",
          "    pm.test('JSON válido', function() { pm.response.to.be.json; });",
          "}"
        ]
      }
    }
  ]
}